passer_web_client/__init__.py
passer_web_client/api.py
passer_web_client/exceptions.py
passer_web_client/passer_web.py
passer_web_client-0.3.0.dist-info/METADATA
passer_web_client-0.3.0.dist-info/WHEEL
passer_web_client-0.3.0.dist-info/top_level.txt
passer_web_client-0.3.0.dist-info/RECORD
