Metadata-Version: 2.1
Name: passer-web-client
Version: 0.3.0
Summary: The client of passer-ground!
Home-page: https://xymedimg.coding.net/public/data-manage-platform/passer-web-client/git
Author: Daryl.Xu
Author-email: xuziqiang@zyheal.com
License: UNKNOWN
Platform: UNKNOWN
Classifier: Programming Language :: Python :: 3.6
Classifier: Operating System :: OS Independent
Requires-Dist: requests
Requires-Dist: dicomweb-client
Requires-Dist: requests-toolbelt
